dirty.py
pytest_dirty-0.0.1.dist-info/licenses/LICENSE
pytest_dirty-0.0.1.dist-info/METADATA
pytest_dirty-0.0.1.dist-info/WHEEL
pytest_dirty-0.0.1.dist-info/entry_points.txt
pytest_dirty-0.0.1.dist-info/top_level.txt
pytest_dirty-0.0.1.dist-info/zip-safe
pytest_dirty-0.0.1.dist-info/RECORD
